table_detector/__init__.py
table_detector/__init__.pyi
table_detector/model.py
table_detector/data/__init__.py
table_detector/data/data.py
moveread_table_detector-0.1.0.dist-info/METADATA
moveread_table_detector-0.1.0.dist-info/WHEEL
moveread_table_detector-0.1.0.dist-info/top_level.txt
moveread_table_detector-0.1.0.dist-info/RECORD
